cuser/__init__.py
cuser/admin.py
cuser/apps.py
cuser/forms.py
cuser/models.py
cuser/settings.py
cuser/migrations/0001_initial.py
cuser/migrations/0002_alter_user_last_name_max_length.py
cuser/migrations/0003_alter_user_first_name_max_length.py
cuser/migrations/__init__.py
cuser/templates/admin/cuser/cuser/add_form.html
django_username_email-2.5.7.dist-info/licenses/LICENSE
django_username_email-2.5.7.dist-info/METADATA
django_username_email-2.5.7.dist-info/WHEEL
django_username_email-2.5.7.dist-info/top_level.txt
django_username_email-2.5.7.dist-info/RECORD
